<?xml version="1.0"?>
<!DOCTYPE hibernate-mapping PUBLIC
        "-//Hibernate/Hibernate Mapping DTD 3.0//EN"
        "http://hibernate.sourceforge.net/hibernate-mapping-3.0.dtd">

<hibernate-mapping package="com.topcoder.web.winformula.model">

    <class name="Submission" table="submission">
        <id name="id" column="submission_id">
            <generator class="com.topcoder.web.common.model.IdGenerator">
                <param name="sequence_name">WINFORMULA_SUBMISSION_SEQ</param>
            </generator>
        </id>
        <many-to-one name="submitter" column="submitter_id" class="com.topcoder.web.common.model.User"/>
        <many-to-one name="contest" column="contest_id" class="Contest"/>
        <property name="originalFileName" column="original_file_name"/>
        <property name="systemFileName" column="system_file_name"/>
        <!--
                <property name="submissionDate" column="submission_date" />
        -->
        <property name="createDate" column="create_date" insert="false" update="false"/>
        <property name="rank"/>
        <property name="height"/>
        <property name="width"/>
        <many-to-one name="path" column="path_id" class="FilePath" cascade="save-update"/>
        <many-to-one name="type" column="submission_type_id" class="SubmissionType"/>
        <many-to-one name="status" column="submission_status_id" class="SubmissionStatus"/>
        <many-to-one name="mimeType" column="mime_type_id" class="MimeType"
                     cascade="none"/>
        <one-to-one name="review" class="SubmissionReview"/>
        <one-to-one name="result" class="ContestResult" cascade="save-update"/>
        <many-to-one name="ORSubmission" column="or_submission_id" class="com.topcoder.web.common.model.comp.Submission" cascade="none"/>
        <set name="prizes" table="submission_prize_xref" cascade="all" sort="natural">
            <key column="submission_id" not-null="true"/>
            <many-to-many column="prize_id" class="Prize"/>
        </set>

    </class>
</hibernate-mapping>